ovos_date_parser/__init__.py
ovos_date_parser/common.py
ovos_date_parser/dates_az.py
ovos_date_parser/dates_ca.py
ovos_date_parser/dates_cs.py
ovos_date_parser/dates_da.py
ovos_date_parser/dates_de.py
ovos_date_parser/dates_en.py
ovos_date_parser/dates_es.py
ovos_date_parser/dates_eu.py
ovos_date_parser/dates_fa.py
ovos_date_parser/dates_fr.py
ovos_date_parser/dates_gl.py
ovos_date_parser/dates_hu.py
ovos_date_parser/dates_it.py
ovos_date_parser/dates_nl.py
ovos_date_parser/dates_pl.py
ovos_date_parser/dates_pt.py
ovos_date_parser/dates_ru.py
ovos_date_parser/dates_sl.py
ovos_date_parser/dates_sv.py
ovos_date_parser/dates_uk.py
ovos_date_parser/version.py
ovos_date_parser/res/az/date_time.json
ovos_date_parser/res/az/date_time_test.json
ovos_date_parser/res/az/date_words.json
ovos_date_parser/res/ca/date_time.json
ovos_date_parser/res/ca/date_time_test.json
ovos_date_parser/res/ca/date_words.json
ovos_date_parser/res/cs/date_time.json
ovos_date_parser/res/cs/date_time_test.json
ovos_date_parser/res/cs/date_words.json
ovos_date_parser/res/da/date_time.json
ovos_date_parser/res/da/date_time_test.json
ovos_date_parser/res/da/date_words.json
ovos_date_parser/res/de/date_time.json
ovos_date_parser/res/de/date_time_test.json
ovos_date_parser/res/de/date_words.json
ovos_date_parser/res/en/date_time.json
ovos_date_parser/res/en/date_time_test.json
ovos_date_parser/res/en/date_words.json
ovos_date_parser/res/es/date_words.json
ovos_date_parser/res/eu/date_time.json
ovos_date_parser/res/eu/date_words.json
ovos_date_parser/res/fa/date_time.json
ovos_date_parser/res/fa/date_time_test.json
ovos_date_parser/res/fa/date_words.json
ovos_date_parser/res/fr/date_time.json
ovos_date_parser/res/fr/date_time_test.json
ovos_date_parser/res/fr/date_words.json
ovos_date_parser/res/gl/date_words.json
ovos_date_parser/res/hu/date_time.json
ovos_date_parser/res/hu/date_time_test.json
ovos_date_parser/res/hu/date_words.json
ovos_date_parser/res/it/date_time.json
ovos_date_parser-0.6.5.dist-info/METADATA
ovos_date_parser-0.6.5.dist-info/WHEEL
ovos_date_parser-0.6.5.dist-info/top_level.txt
ovos_date_parser-0.6.5.dist-info/RECORD
