Metadata-Version: 2.1
Name: ovos-date-parser
Version: 0.6.5
Summary: OpenVoiceOS's multilingual text parsing and formatting library
Home-page: https://github.com/OpenVoiceOS/ovos-date-parser
Author: Mycroft AI / OVOS
Author-email: jarbasai@mailfence.com
License: Apache2.0
Classifier: Development Status :: 4 - Beta
Classifier: Intended Audience :: Developers
Classifier: Topic :: Text Processing :: Linguistic
Classifier: License :: OSI Approved :: Apache Software License
Classifier: Programming Language :: Python :: 3.6
Classifier: Programming Language :: Python :: 3.7
Classifier: Programming Language :: Python :: 3.8
Classifier: Programming Language :: Python :: 3.9
Requires-Dist: python-dateutil~=2.6
Requires-Dist: quebra-frases>=0.3.7
Requires-Dist: ovos-number-parser<1.0.0,>=0.4.1
Requires-Dist: dateparser
Requires-Dist: ovos-config
